ElevatorController.v
`timescale 1ns / 1ps

module ElevatorController (
    input clk,
    input reset,
    input up_request,
    input down_request,
    input [1:0] current_floor,
    input [1:0] target_floor,
    input emergency_stop,
    output reg move_up,
    output reg move_down,
    output reg door_open,
    output reg stopped,
    output reg [2:0] state  // For debugging
);

// State encoding
localparam IDLE            = 3'b000,
           MOVING_UP       = 3'b001,
           MOVING_DOWN     = 3'b010,
           DOOR_OPEN       = 3'b011,
           EMERGENCY_STOP  = 3'b100;

reg [3:0] door_timer;
reg [2:0] next_state;

// FSM State Transition
always @(posedge clk or posedge reset) begin
    if (reset)
        state <= IDLE;
    else
        state <= next_state;
end

// FSM Next State Logic
always @(*) begin
    case (state)
        IDLE: begin
            if (emergency_stop)
                next_state = EMERGENCY_STOP;
            else if (up_request && current_floor < target_floor)
                next_state = MOVING_UP;
            else if (down_request && current_floor > target_floor)
                next_state = MOVING_DOWN;
            else
                next_state = IDLE;
        end

        MOVING_UP: begin
            if (emergency_stop)
                next_state = EMERGENCY_STOP;
            else if (current_floor == target_floor)
                next_state = DOOR_OPEN;
            else
                next_state = MOVING_UP;
        end

        MOVING_DOWN: begin
            if (emergency_stop)
                next_state = EMERGENCY_STOP;
            else if (current_floor == target_floor)
                next_state = DOOR_OPEN;
            else
                next_state = MOVING_DOWN;
        end

        DOOR_OPEN: begin
            if (emergency_stop)
                next_state = EMERGENCY_STOP;
            else if (door_timer == 0)
                next_state = IDLE;
            else
                next_state = DOOR_OPEN;
        end

        EMERGENCY_STOP: begin
            if (!emergency_stop)
                next_state = IDLE; // Go back to idle after emergency clears
            else
                next_state = EMERGENCY_STOP;
        end

        default: next_state = IDLE;
    endcase
end

// FSM Output Logic and door timer
always @(posedge clk or posedge reset) begin
    if (reset) begin
        move_up    <= 0;
        move_down  <= 0;
        door_open  <= 0;
        stopped    <= 1;
        door_timer <= 0;
    end else begin
        case (state)
            IDLE: begin
                move_up    <= 0;
                move_down  <= 0;
                door_open  <= 0;
                stopped    <= 1;
                door_timer <= 0;
            end

            MOVING_UP: begin
                move_up    <= 1;
                move_down  <= 0;
                door_open  <= 0;
                stopped    <= 0;
            end

            MOVING_DOWN: begin
                move_up    <= 0;
                move_down  <= 1;
                door_open  <= 0;
                stopped    <= 0;
            end

            DOOR_OPEN: begin
                move_up    <= 0;
                move_down  <= 0;
                door_open  <= 1;
                stopped    <= 1;
                if (door_timer == 0)
                    door_timer <= 4;  // Keep door open for 4 cycles
                else
                    door_timer <= door_timer - 1;
            end

            EMERGENCY_STOP: begin
                move_up    <= 0;
                move_down  <= 0;
                door_open  <= 0;
                stopped    <= 1;
                door_timer <= 0;
            end

            default: begin
                move_up    <= 0;
                move_down  <= 0;
                door_open  <= 0;
                stopped    <= 1;
                door_timer <= 0;
            end
        endcase
    end
end

endmodule

ElevatorController_tb.v
`timescale 1ns / 1ps

module ElevatorController_tb;

reg clk, reset;
reg up_request, down_request;
reg [1:0] current_floor, target_floor;
reg emergency_stop;

wire move_up, move_down, door_open, stopped;
wire [2:0] state;

ElevatorController dut (
    .clk(clk),
    .reset(reset),
    .up_request(up_request),
    .down_request(down_request),
    .current_floor(current_floor),
    .target_floor(target_floor),
    .emergency_stop(emergency_stop),
    .move_up(move_up),
    .move_down(move_down),
    .door_open(door_open),
    .stopped(stopped),
    .state(state)
);

// Clock generation
initial clk = 0;
always #5 clk = ~clk; // 10ns clock cycle

initial begin
    $dumpfile("ElevatorController.vcd");
    $dumpvars(0, ElevatorController_tb);

    // Initialize
    reset = 1;
    up_request = 0;
    down_request = 0;
    current_floor = 2'b00;
    target_floor = 2'b00;
    emergency_stop = 0;

    #10 reset = 0;

    // Test up request from floor 0 to 3
    current_floor = 2'b00; target_floor = 2'b11;
    up_request = 1; #10;
    up_request = 0;

    // Simulate arrival at target floor
    #50 current_floor = 2'b01;
    #50 current_floor = 2'b10;
    #50 current_floor = 2'b11;

    // Door opens at target floor
    #50;

    // Emergency during door open
    emergency_stop = 1; #20;
    emergency_stop = 0;

    // Test down request from floor 3 to 1
    current_floor = 2'b11; target_floor = 2'b01;
    down_request = 1; #10;
    down_request = 0;

    #50 current_floor = 2'b10;
    #50 current_floor = 2'b01;

    // Let door open and close
    #100;

    $finish;
end

initial begin
    $monitor("Time: %3t | Floor: %b | Target: %b | Up: %b | Down: %b | MoveUp: %b | MoveDown: %b | Door: %b | Emergency: %b | State: %b",
             $time, current_floor, target_floor, up_request, down_request,
             move_up, move_down, door_open, emergency_stop, state);
end

endmodule

ElevatorController.vcd
$date
	Tue Jun 17 00:22:33 2025
$end
$version
	Icarus Verilog
$end
$timescale
	1ps
$end
$scope module ElevatorController_tb $end
$var wire 1 ! stopped $end
$var wire 3 " state [2:0] $end
$var wire 1 # move_up $end
$var wire 1 $ move_down $end
$var wire 1 % door_open $end
$var reg 1 & clk $end
$var reg 2 ' current_floor [1:0] $end
$var reg 1 ( down_request $end
$var reg 1 ) emergency_stop $end
$var reg 1 * reset $end
$var reg 2 + target_floor [1:0] $end
$var reg 1 , up_request $end
$scope module dut $end
$var wire 1 & clk $end
$var wire 2 - current_floor [1:0] $end
$var wire 1 ( down_request $end
$var wire 1 ) emergency_stop $end
$var wire 1 * reset $end
$var wire 2 . target_floor [1:0] $end
$var wire 1 , up_request $end
$var parameter 3 / DOOR_OPEN $end
$var parameter 3 0 EMERGENCY_STOP $end
$var parameter 3 1 IDLE $end
$var parameter 3 2 MOVING_DOWN $end
$var parameter 3 3 MOVING_UP $end
$var reg 1 % door_open $end
$var reg 4 4 door_timer [3:0] $end
$var reg 1 $ move_down $end
$var reg 1 # move_up $end
$var reg 3 5 next_state [2:0] $end
$var reg 3 6 state [2:0] $end
$var reg 1 ! stopped $end
$upscope $end
$upscope $end
$enddefinitions $end
$comment Show the parameter values. $end
$dumpall
b1 3
b10 2
b0 1
b100 0
b11 /
$end
#0
$dumpvars
b0 6
b0 5
b0 4
b0 .
b0 -
0,
b0 +
1*
0)
0(
b0 '
0&
0%
0$
0#
b0 "
1!
$end
#5000
1&
#10000
b1 5
0&
1,
b11 +
b11 .
0*
#15000
b1 "
b1 6
1&
#20000
0&
0,
#25000
0!
1#
1&
#30000
0&
#35000
1&
#40000
0&
#45000
1&
#50000
0&
#55000
1&
#60000
0&
#65000
1&
#70000
0&
b1 '
b1 -
#75000
1&
#80000
0&
#85000
1&
#90000
0&
#95000
1&
#100000
0&
#105000
1&
#110000
0&
#115000
1&
#120000
0&
b10 '
b10 -
#125000
1&
#130000
0&
#135000
1&
#140000
0&
#145000
1&
#150000
0&
#155000
1&
#160000
0&
#165000
1&
#170000
b11 5
0&
b11 '
b11 -
#175000
b0 5
b11 "
b11 6
1&
#180000
0&
#185000
b100 4
1!
1%
0#
b0 "
b0 6
1&
#190000
0&
#195000
b0 4
0%
1&
#200000
0&
#205000
1&
#210000
0&
#215000
1&
#220000
b100 5
0&
1)
#225000
b100 "
b100 6
1&
#230000
0&
#235000
1&
#240000
b0 5
0&
1(
b1 +
b1 .
0)
#245000
b10 5
b0 "
b0 6
1&
#250000
b0 5
0&
0(
#255000
1&
#260000
0&
#265000
1&
#270000
0&
#275000
1&
#280000
0&
#285000
1&
#290000
0&
#295000
1&
#300000
0&
b10 '
b10 -
#305000
1&
#310000
0&
#315000
1&
#320000
0&
#325000
1&
#330000
0&
#335000
1&
#340000
0&
#345000
1&
#350000
0&
b1 '
b1 -
